miyadaiku/themes/popper_js/__init__.py
miyadaiku/themes/popper_js/__version__.py
miyadaiku/themes/popper_js/config.yml
miyadaiku/themes/popper_js/externals/popper-utils.js
miyadaiku/themes/popper_js/externals/popper-utils.min.js
miyadaiku/themes/popper_js/externals/popper.js
miyadaiku/themes/popper_js/externals/popper.min.js
miyadaiku/themes/popper_js/templates/macros.html
miyadaiku.themes.popper_js-0.1.dist-info/METADATA
miyadaiku.themes.popper_js-0.1.dist-info/WHEEL
miyadaiku.themes.popper_js-0.1.dist-info/top_level.txt
miyadaiku.themes.popper_js-0.1.dist-info/RECORD
