Metadata-Version: 2.1
Name: miyadaiku.themes.popper-js
Version: 0.1
Summary: Popper.js files for miyadaiku static site generator
Home-page: https://github.com/miyadaiku/miyadaiku-themes-popper_js
Author: Atsuo Ishimoto
Author-email: UNKNOWN
License: MIT
Project-URL: Miyadaiku, https://miyadaiku.github.io/
Platform: UNKNOWN
Classifier: Programming Language :: Python :: 3
Classifier: Programming Language :: Python :: 3.6
Classifier: Programming Language :: Python :: 3.7
Requires-Dist: miyadaiku
